{
  "fr": {
    "new": "Nouvelle section",
    "load": "Charger un Bookmark",
    "download": "Sauvegarder un Bookmark",
    "delete": "Tout effacer",
    "infoText": "Entrez une URL pour l'afficher dans cette fenêtre",
    "title": "Gestion des signets",
    "editModeOn": "Mode Édition",
    "editModeOff": "Quitter Édition",
    "login": "Connexion",
    "logout": "Déconnexion",
    "languageName": "Français"
  },
  "en": {
    "new": "New Section",
    "load": "Load Bookmark",
    "download": "Download Bookmark",
    "delete": "Delete all",
    "infoText": "Enter URL to display it in this window.",
    "title": "Bookmarks Manager",
    "editModeOn": "Edit Mode",
    "editModeOff": "Exit Edit Mode",
    "login": "Login",
    "logout": "Logout",
    "languageName": "English"
  },
  "es": {
    "new": "Nueva sección",
    "load": "Cargar Marcador",
    "download": "Guardar Marcador",
    "delete": "Borrar todo",
    "infoText": "Introduce una URL para mostrarla en esta ventana",
    "title": "Gestor de Marcadores",
    "editModeOn": "Modo Edición",
    "editModeOff": "Salir del Modo Edición",
    "login": "Iniciar sesión",
    "logout": "Cerrar sesión",
    "languageName": "Español"
  },
  "de": {
    "new": "Neuer Abschnitt",
    "load": "Lesezeichen laden",
    "download": "Lesezeichen speichern",
    "delete": "Alles löschen",
    "infoText": "Geben Sie eine URL ein, um sie in diesem Fenster anzuzeigen",
    "title": "Lesezeichen-Manager",
    "editModeOn": "Bearbeitungsmodus",
    "editModeOff": "Bearbeitungsmodus verlassen",
    "login": "Anmelden",
    "logout": "Abmelden",
    "languageName": "Deutsch"
  },
  "it": {
    "new": "Nuova sezione",
    "load": "Carica segnalibro",
    "download": "Salva segnalibro",
    "delete": "Cancella tutto",
    "infoText": "Inserisci un URL per visualizzarlo in questa finestra",
    "title": "Gestore dei segnalibri",
    "editModeOn": "Modalità Modifica",
    "editModeOff": "Esci dalla Modifica",
    "login": "Accedi",
    "logout": "Esci",
    "languageName": "Italiano"
  },
  "pt": {
    "new": "Nova seção",
    "load": "Carregar marcador",
    "download": "Baixar marcador",
    "delete": "Apagar tudo",
    "infoText": "Digite um URL para exibi-lo nesta janela",
    "title": "Gerenciador de Marcadores",
    "editModeOn": "Modo de Edição",
    "editModeOff": "Sair do Modo de Edição",
    "login": "Entrar",
    "logout": "Sair",
    "languageName": "Português"
  },
  "ru": {
    "new": "Новый раздел",
    "load": "Загрузить закладку",
    "download": "Сохранить закладку",
    "delete": "Удалить всё",
    "infoText": "Введите URL для отображения в этом окне",
    "title": "Менеджер Закладок",
    "editModeOn": "Режим Редактирования",
    "editModeOff": "Выйти из Режима Редактирования",
    "login": "Войти",
    "logout": "Выйти",
    "languageName": "Русский"
  },
  "ja": {
    "new": "新しいセクション",
    "load": "ブックマークを読み込む",
    "download": "ブックマークを保存",
    "delete": "すべて削除",
    "infoText": "このウィンドウに表示するURLを入力してください",
    "title": "ブックマークマネージャー",
    "editModeOn": "編集モード",
    "editModeOff": "編集モードを終了",
    "login": "ログイン",
    "logout": "ログアウト",
    "languageName": "日本語"
  },
  "zh": {
    "new": "新建部分",
    "load": "加载书签",
    "download": "保存书签",
    "delete": "删除所有",
    "infoText": "输入网址以在此窗口中显示",
    "title": "书签管理器",
    "editModeOn": "编辑模式",
    "editModeOff": "退出编辑模式",
    "login": "登录",
    "logout": "登出",
    "languageName": "中文"
  },
  "ar": {
    "new": "قسم جديد",
    "load": "تحميل الإشارة المرجعية",
    "download": "حفظ الإشارة المرجعية",
    "delete": "حذف الكل",
    "infoText": "أدخل عنوان URL لعرضه في هذه النافذة",
    "title": "مدير الإشارات المرجعية",
    "editModeOn": "وضع التعديل",
    "editModeOff": "الخروج من وضع التعديل",
    "login": "تسجيل الدخول",
    "logout": "تسجيل الخروج",
    "languageName": "العربية"
  },
  "hi": {
    "new": "नया अनुभाग",
    "load": "बुकमार्क लोड करें",
    "download": "बुकमार्क सहेजें",
    "delete": "सभी हटाएं",
    "infoText": "इस विंडो में दिखाने के लिए URL दर्ज करें",
    "title": "बुकमार्क प्रबंधक",
    "editModeOn": "संपादन मोड",
    "editModeOff": "संपादन मोड से बाहर निकलें",
    "login": "लॉग इन करें",
    "logout": "लॉग आउट करें",
    "languageName": "हिन्दी"
  },
  "ko": {
    "new": "새 섹션",
    "load": "북마크 로드",
    "download": "북마크 저장",
    "delete": "모두 삭제",
    "infoText": "이 창에 표시할 URL을 입력하세요",
    "title": "북마크 관리자",
    "editModeOn": "편집 모드",
    "editModeOff": "편집 모드 종료",
    "login": "로그인",
    "logout": "로그아웃",
    "languageName": "한국어"
  },
  "nl": {
    "new": "Nieuwe sectie",
    "load": "Bladwijzer laden",
    "download": "Bladwijzer opslaan",
    "delete": "Alles verwijderen",
    "infoText": "Voer een URL in om deze in dit venster weer te geven",
    "title": "Bladwijzerbeheer",
    "editModeOn": "Bewerkingsmodus",
    "editModeOff": "Bewerkingsmodus verlaten",
    "login": "Inloggen",
    "logout": "Uitloggen",
    "languageName": "Nederlands"
  },
  "tr": {
    "new": "Yeni bölüm",
    "load": "Yer İşaretini Yükle",
    "download": "Yer İşaretini Kaydet",
    "delete": "Hepsini Sil",
    "infoText": "Bu pencerede görüntülemek için bir URL girin",
    "title": "Yer İmi Yöneticisi",
    "editModeOn": "Düzenleme Modu",
    "editModeOff": "Düzenleme Modundan Çık",
    "login": "Giriş Yap",
    "logout": "Çıkış Yap",
    "languageName": "Türkçe"
  }
}
